chem_mat_data/.env
chem_mat_data/ChemMatData_logo_final.png
chem_mat_data/VERSION
chem_mat_data/__init__.py
chem_mat_data/_typing.py
chem_mat_data/cache.py
chem_mat_data/cli.py
chem_mat_data/config.py
chem_mat_data/connectors.py
chem_mat_data/data.py
chem_mat_data/dataset.py
chem_mat_data/graph.py
chem_mat_data/main.py
chem_mat_data/manage.py
chem_mat_data/metadata.yml
chem_mat_data/metadata.yml.backup
chem_mat_data/processing.py
chem_mat_data/testing.py
chem_mat_data/utils.py
chem_mat_data/visualization.py
chem_mat_data/web.py
chem_mat_data/examples/00_quickstart.ipynb
chem_mat_data/examples/01_gnn_demo.ipynb
chem_mat_data/examples/_test.py
chem_mat_data/examples/clintox.csv
chem_mat_data/examples/clintox.mpack
chem_mat_data/examples/clintox.mpack.gz
chem_mat_data/scripts/README.rst
chem_mat_data/scripts/_clean_qm9.ipynb
chem_mat_data/scripts/create_graph_datasets.py
chem_mat_data/scripts/create_graph_datasets__ames.py
chem_mat_data/scripts/create_graph_datasets__aqsoldb.py
chem_mat_data/scripts/create_graph_datasets__bace_cls.py
chem_mat_data/scripts/create_graph_datasets__bace_reg.py
chem_mat_data/scripts/create_graph_datasets__bbbp.py
chem_mat_data/scripts/create_graph_datasets__beet.py
chem_mat_data/scripts/create_graph_datasets__clintox.py
chem_mat_data/scripts/create_graph_datasets__compas_1x.py
chem_mat_data/scripts/create_graph_datasets__compas_2x.py
chem_mat_data/scripts/create_graph_datasets__compas_3x.py
chem_mat_data/scripts/create_graph_datasets__dpp4.py
chem_mat_data/scripts/create_graph_datasets__elanos_bp.py
chem_mat_data/scripts/create_graph_datasets__elanos_vp.py
chem_mat_data/scripts/create_graph_datasets__esol.py
chem_mat_data/scripts/create_graph_datasets__freesolv.py
chem_mat_data/scripts/create_graph_datasets__from_tu.py
chem_mat_data/scripts/create_graph_datasets__from_tu__MCF_7.py
chem_mat_data/scripts/create_graph_datasets__from_tu__MOLT_4.py
chem_mat_data/scripts/create_graph_datasets__from_tu__OVCAR_8.py
chem_mat_database-1.3.0.dist-info/METADATA
chem_mat_database-1.3.0.dist-info/WHEEL
chem_mat_database-1.3.0.dist-info/entry_points.txt
chem_mat_database-1.3.0.dist-info/licenses/LICENSE
chem_mat_database-1.3.0.dist-info/RECORD
