Metadata-Version: 2.4
Name: chem_mat_database
Version: 1.3.0
Summary: Command Line Interface for projects
Author-email: Jonas Teufel <jonseb1998@gmail.com>, Mohit Singh <mohit.singh@student.kit.edu>
Maintainer-email: Jonas Teufel <jonseb1998@gmail.com>
License: MIT License
License-File: LICENSE
Keywords: chemistry,data,data management,dataset,graph neural network,graph representation,machine learning
Classifier: Development Status :: 4 - Beta
Classifier: Intended Audience :: Developers
Classifier: License :: OSI Approved :: MIT License
Classifier: Programming Language :: Python :: 3.8
Classifier: Programming Language :: Python :: 3.9
Classifier: Programming Language :: Python :: 3.10
Classifier: Programming Language :: Python :: 3.11
Classifier: Programming Language :: Python :: 3.12
Classifier: Topic :: Software Development
Requires-Python: <=3.12,>=3.8
Requires-Dist: appdirs<2.0,>=1.4.4
Requires-Dist: ase<4.0,>=3.23.0
Requires-Dist: cairosvg>=2.7.1
Requires-Dist: imageio>=2.34.0
Requires-Dist: jinja2>=3.0.0
Requires-Dist: lorem==0.1.1
Requires-Dist: matplotlib>=3.4.0
Requires-Dist: msgpack-numpy>=0.4.8
Requires-Dist: msgpack>=1.0.2
Requires-Dist: networkx<=3.3
Requires-Dist: numpy<2.0,>=1.21.0
Requires-Dist: openpyxl<4.0,>=3.0.10
Requires-Dist: pandas<2.2.2
Requires-Dist: parsimonious<1.0,>=0.10.0
Requires-Dist: prettytable<4.0,>=3.6.0
Requires-Dist: pycomex>=0.23.0
Requires-Dist: pydantic<2.0,>=1.10.0
Requires-Dist: python-dotenv==1.0.1
Requires-Dist: pyyaml>=6.0.0
Requires-Dist: rdkit>=2023.0.0
Requires-Dist: requests>=2.30.0
Requires-Dist: rich-click>=1.8.0
Requires-Dist: tomlkit<1.0,>=0.13.2
Provides-Extra: dev
Requires-Dist: build>=0.10.0; extra == 'dev'
Requires-Dist: jax>=0.4.0; extra == 'dev'
Requires-Dist: jaxlib>=0.4.0; extra == 'dev'
Requires-Dist: jraph>=0.0.6.dev0; extra == 'dev'
Requires-Dist: mypy>=1.0.0; extra == 'dev'
Requires-Dist: nox[uv]>=2023.4.22; extra == 'dev'
Requires-Dist: pytest-cov>=4.0.0; extra == 'dev'
Requires-Dist: pytest>=7.0.0; extra == 'dev'
Requires-Dist: ruff>=0.1.0; extra == 'dev'
Requires-Dist: sphinx-rtd-theme>=1.3.0; extra == 'dev'
Requires-Dist: sphinx>=6.0.0; extra == 'dev'
Requires-Dist: torch-geometric>=2.3.0; extra == 'dev'
Requires-Dist: torch>=1.13.0; extra == 'dev'
Requires-Dist: types-requests>=2.31.0; extra == 'dev'
